blue/__init__.py
blue/__main__.py
blue-0.9.1.dist-info/LICENSE
blue-0.9.1.dist-info/METADATA
blue-0.9.1.dist-info/WHEEL
blue-0.9.1.dist-info/entry_points.txt
blue-0.9.1.dist-info/top_level.txt
blue-0.9.1.dist-info/RECORD
