Metadata-Version: 2.1
Name: blue
Version: 0.9.1
Summary: Blue -- Some folks like black but I prefer blue.
Home-page: https://blue.readthedocs.io/
Author: Grant Jenks
Author-email: contact@grantjenks.com
License: Apache 2.0
Project-URL: Documentation, https://blue.readthedocs.io/en/latest
Project-URL: Source, https://github.com/grantjenks/blue.git
Project-URL: Tracker, https://github.com/grantjenks/blue/issues
Platform: UNKNOWN
Classifier: Development Status :: 2 - Pre-Alpha
Classifier: Intended Audience :: Developers
Classifier: License :: OSI Approved :: Apache Software License
Classifier: Natural Language :: English
Classifier: Programming Language :: Python
Classifier: Programming Language :: Python :: 3
Classifier: Programming Language :: Python :: 3.6
Classifier: Programming Language :: Python :: 3.7
Classifier: Programming Language :: Python :: 3.8
Classifier: Programming Language :: Python :: 3.9
Classifier: Programming Language :: Python :: Implementation :: CPython
License-File: LICENSE
